<?xml version="1.0" encoding="utf-8" ?>
<dwsync>
<file name="classtrees_com-tecnick-tcpdf.html" server="hot//crm/" local="129789909600000000" remote="129789909600000000" />
<file name="classtrees_JAMA.html" server="hot//crm/" local="129789909600000000" remote="129789909600000000" />
<file name="classtrees_Math_Stats.html" server="hot//crm/" local="129789909600000000" remote="129789909600000000" />
<file name="classtrees_PHPExcel.html" server="hot//crm/" local="129789909600000000" remote="129789909600000000" />
<file name="classtrees_PHPExcel_CachedObjectStorage.html" server="hot//crm/" local="129789909600000000" remote="129789909600000000" />
<file name="classtrees_PHPExcel_Calculation.html" server="hot//crm/" local="129789909600000000" remote="129789909600000000" />
<file name="classtrees_PHPExcel_Cell.html" server="hot//crm/" local="129789909600000000" remote="129789909600000000" />
<file name="classtrees_PHPExcel_Reader.html" server="hot//crm/" local="129789909600000000" remote="129789909600000000" />
<file name="classtrees_PHPExcel_Reader_Excel2007.html" server="hot//crm/" local="129789909600000000" remote="129789909600000000" />
<file name="classtrees_PHPExcel_Reader_Excel5.html" server="hot//crm/" local="129789909600000000" remote="129789909600000000" />
<file name="classtrees_PHPExcel_RichText.html" server="hot//crm/" local="129789909600000000" remote="129789909600000000" />
<file name="classtrees_PHPExcel_Settings.html" server="hot//crm/" local="129789909600000000" remote="129789909600000000" />
<file name="classtrees_PHPExcel_Shared.html" server="hot//crm/" local="129789909600000000" remote="129789909600000000" />
<file name="classtrees_PHPExcel_Shared_Best_Fit.html" server="hot//crm/" local="129789909600000000" remote="129789909600000000" />
<file name="classtrees_PHPExcel_Shared_Escher.html" server="hot//crm/" local="129789909600000000" remote="129789909600000000" />
<file name="classtrees_PHPExcel_Shared_OLE.html" server="hot//crm/" local="129789909600000000" remote="129789909600000000" />
<file name="classtrees_PHPExcel_Shared_ZipArchive.html" server="hot//crm/" local="129789909600000000" remote="129789909600000000" />
<file name="classtrees_PHPExcel_Style.html" server="hot//crm/" local="129789909600000000" remote="129789909600000000" />
<file name="classtrees_PHPExcel_Worksheet.html" server="hot//crm/" local="129789909600000000" remote="129789909600000000" />
<file name="classtrees_PHPExcel_Worksheet_Drawing.html" server="hot//crm/" local="129789909600000000" remote="129789909600000000" />
<file name="classtrees_PHPExcel_Writer.html" server="hot//crm/" local="129789909600000000" remote="129789909600000000" />
<file name="classtrees_PHPExcel_Writer_Excel2007.html" server="hot//crm/" local="129789909600000000" remote="129789909600000000" />
<file name="classtrees_PHPExcel_Writer_Excel5.html" server="hot//crm/" local="129789909600000000" remote="129789909600000000" />
<file name="elementindex.html" server="hot//crm/" local="129789909600000000" remote="129789909600000000" />
<file name="elementindex_com-tecnick-tcpdf.html" server="hot//crm/" local="129789909600000000" remote="129789909600000000" />
<file name="elementindex_JAMA.html" server="hot//crm/" local="129789909600000000" remote="129789909600000000" />
<file name="elementindex_Math_Stats.html" server="hot//crm/" local="129789909600000000" remote="129789909600000000" />
<file name="elementindex_PHPExcel.html" server="hot//crm/" local="129789909600000000" remote="129789909600000000" />
<file name="elementindex_PHPExcel_CachedObjectStorage.html" server="hot//crm/" local="129789909600000000" remote="129789909600000000" />
<file name="elementindex_PHPExcel_Calculation.html" server="hot//crm/" local="129789909600000000" remote="129789909600000000" />
<file name="elementindex_PHPExcel_Cell.html" server="hot//crm/" local="129789909600000000" remote="129789909600000000" />
<file name="elementindex_PHPExcel_Reader.html" server="hot//crm/" local="129789909600000000" remote="129789909600000000" />
<file name="elementindex_PHPExcel_Reader_Excel2007.html" server="hot//crm/" local="129789909600000000" remote="129789909600000000" />
<file name="elementindex_PHPExcel_Reader_Excel5.html" server="hot//crm/" local="129789909600000000" remote="129789909600000000" />
<file name="elementindex_PHPExcel_RichText.html" server="hot//crm/" local="129789909600000000" remote="129789909600000000" />
<file name="elementindex_PHPExcel_Settings.html" server="hot//crm/" local="129789909600000000" remote="129789909600000000" />
<file name="elementindex_PHPExcel_Shared.html" server="hot//crm/" local="129789909600000000" remote="129789909600000000" />
<file name="elementindex_PHPExcel_Shared_Best_Fit.html" server="hot//crm/" local="129789909600000000" remote="129789909600000000" />
<file name="elementindex_PHPExcel_Shared_Escher.html" server="hot//crm/" local="129789909600000000" remote="129789909600000000" />
<file name="elementindex_PHPExcel_Shared_OLE.html" server="hot//crm/" local="129789909600000000" remote="129789909600000000" />
<file name="elementindex_PHPExcel_Shared_ZipArchive.html" server="hot//crm/" local="129789909600000000" remote="129789909600000000" />
<file name="elementindex_PHPExcel_Style.html" server="hot//crm/" local="129789909600000000" remote="129789909600000000" />
<file name="elementindex_PHPExcel_Worksheet.html" server="hot//crm/" local="129789909600000000" remote="129789909600000000" />
<file name="elementindex_PHPExcel_Worksheet_Drawing.html" server="hot//crm/" local="129789909600000000" remote="129789909600000000" />
<file name="elementindex_PHPExcel_Writer.html" server="hot//crm/" local="129789909600000000" remote="129789909600000000" />
<file name="elementindex_PHPExcel_Writer_Excel2007.html" server="hot//crm/" local="129789909600000000" remote="129789909600000000" />
<file name="elementindex_PHPExcel_Writer_Excel5.html" server="hot//crm/" local="129789909600000000" remote="129789909600000000" />
<file name="errors.html" server="hot//crm/" local="129789909600000000" remote="129789909600000000" />
<file name="index.html" server="hot//crm/" local="129789909600000000" remote="129789909600000000" />
<file name="li_com-tecnick-tcpdf.html" server="hot//crm/" local="129789909600000000" remote="129789909600000000" />
<file name="li_JAMA.html" server="hot//crm/" local="129789909600000000" remote="129789909600000000" />
<file name="li_Math_Stats.html" server="hot//crm/" local="129789909600000000" remote="129789909600000000" />
<file name="li_PHPExcel.html" server="hot//crm/" local="129789909600000000" remote="129789909600000000" />
<file name="li_PHPExcel_CachedObjectStorage.html" server="hot//crm/" local="129789909600000000" remote="129789909600000000" />
<file name="li_PHPExcel_Calculation.html" server="hot//crm/" local="129789909600000000" remote="129789909600000000" />
<file name="li_PHPExcel_Cell.html" server="hot//crm/" local="129789909600000000" remote="129789909600000000" />
<file name="li_PHPExcel_Reader.html" server="hot//crm/" local="129789909600000000" remote="129789909600000000" />
<file name="li_PHPExcel_Reader_Excel2007.html" server="hot//crm/" local="129789909600000000" remote="129789909600000000" />
<file name="li_PHPExcel_Reader_Excel5.html" server="hot//crm/" local="129789909600000000" remote="129789909600000000" />
<file name="li_PHPExcel_RichText.html" server="hot//crm/" local="129789909600000000" remote="129789909600000000" />
<file name="li_PHPExcel_Settings.html" server="hot//crm/" local="129789909600000000" remote="129789909600000000" />
<file name="li_PHPExcel_Shared.html" server="hot//crm/" local="129789909600000000" remote="129789909600000000" />
<file name="li_PHPExcel_Shared_Best_Fit.html" server="hot//crm/" local="129789909600000000" remote="129789909600000000" />
<file name="li_PHPExcel_Shared_Escher.html" server="hot//crm/" local="129789909600000000" remote="129789909600000000" />
<file name="li_PHPExcel_Shared_OLE.html" server="hot//crm/" local="129789909600000000" remote="129789909600000000" />
<file name="li_PHPExcel_Shared_ZipArchive.html" server="hot//crm/" local="129789909600000000" remote="129789909600000000" />
<file name="li_PHPExcel_Style.html" server="hot//crm/" local="129789909600000000" remote="129789909600000000" />
<file name="li_PHPExcel_Worksheet.html" server="hot//crm/" local="129789909600000000" remote="129789909600000000" />
<file name="li_PHPExcel_Worksheet_Drawing.html" server="hot//crm/" local="129789909600000000" remote="129789909600000000" />
<file name="li_PHPExcel_Writer.html" server="hot//crm/" local="129789909600000000" remote="129789909600000000" />
<file name="li_PHPExcel_Writer_Excel2007.html" server="hot//crm/" local="129789909600000000" remote="129789909600000000" />
<file name="li_PHPExcel_Writer_Excel5.html" server="hot//crm/" local="129789909600000000" remote="129789909600000000" />
<file name="todolist.html" server="hot//crm/" local="129789909600000000" remote="129789909600000000" />
<file name="classtrees_PHPExcel_Shared_OLE.html" server="//nas/Web/crm/" local="129789909600000000" remote="129789909600000000" />
<file name="classtrees_com-tecnick-tcpdf.html" server="//nas/Web/crm/" local="129789909600000000" remote="129789909600000000" />
<file name="classtrees_PHPExcel_Worksheet_Drawing.html" server="//nas/Web/crm/" local="129789909600000000" remote="129789909600000000" />
<file name="li_PHPExcel_RichText.html" server="//nas/Web/crm/" local="129789909600000000" remote="129789909600000000" />
<file name="classtrees_PHPExcel_Reader_Excel5.html" server="//nas/Web/crm/" local="129789909600000000" remote="129789909600000000" />
<file name="li_PHPExcel_Shared.html" server="//nas/Web/crm/" local="129789909600000000" remote="129789909600000000" />
<file name="li_JAMA.html" server="//nas/Web/crm/" local="129789909600000000" remote="129789909600000000" />
<file name="elementindex_PHPExcel_CachedObjectStorage.html" server="//nas/Web/crm/" local="129789909600000000" remote="129789909600000000" />
<file name="classtrees_PHPExcel_Writer.html" server="//nas/Web/crm/" local="129789909600000000" remote="129789909600000000" />
<file name="li_PHPExcel.html" server="//nas/Web/crm/" local="129789909600000000" remote="129789909600000000" />
<file name="elementindex_PHPExcel_Shared.html" server="//nas/Web/crm/" local="129789909600000000" remote="129789909600000000" />
<file name="classtrees_JAMA.html" server="//nas/Web/crm/" local="129789909600000000" remote="129789909600000000" />
<file name="classtrees_PHPExcel_RichText.html" server="//nas/Web/crm/" local="129789909600000000" remote="129789909600000000" />
<file name="elementindex_PHPExcel_Reader_Excel5.html" server="//nas/Web/crm/" local="129789909600000000" remote="129789909600000000" />
<file name="elementindex_PHPExcel.html" server="//nas/Web/crm/" local="129789909600000000" remote="129789909600000000" />
<file name="li_PHPExcel_Reader_Excel5.html" server="//nas/Web/crm/" local="129789909600000000" remote="129789909600000000" />
<file name="elementindex_Math_Stats.html" server="//nas/Web/crm/" local="129789909600000000" remote="129789909600000000" />
<file name="li_PHPExcel_Writer.html" server="//nas/Web/crm/" local="129789909600000000" remote="129789909600000000" />
<file name="elementindex_PHPExcel_Writer_Excel5.html" server="//nas/Web/crm/" local="129789909600000000" remote="129789909600000000" />
<file name="li_PHPExcel_Reader.html" server="//nas/Web/crm/" local="129789909600000000" remote="129789909600000000" />
<file name="classtrees_PHPExcel_Cell.html" server="//nas/Web/crm/" local="129789909600000000" remote="129789909600000000" />
<file name="elementindex_PHPExcel_Shared_OLE.html" server="//nas/Web/crm/" local="129789909600000000" remote="129789909600000000" />
<file name="elementindex_PHPExcel_Shared_Best_Fit.html" server="//nas/Web/crm/" local="129789909600000000" remote="129789909600000000" />
<file name="elementindex_PHPExcel_Cell.html" server="//nas/Web/crm/" local="129789909600000000" remote="129789909600000000" />
<file name="elementindex_com-tecnick-tcpdf.html" server="//nas/Web/crm/" local="129789909600000000" remote="129789909600000000" />
<file name="classtrees_PHPExcel_Shared_Escher.html" server="//nas/Web/crm/" local="129789909600000000" remote="129789909600000000" />
<file name="classtrees_PHPExcel_Shared.html" server="//nas/Web/crm/" local="129789909600000000" remote="129789909600000000" />
<file name="classtrees_PHPExcel.html" server="//nas/Web/crm/" local="129789909600000000" remote="129789909600000000" />
<file name="elementindex_PHPExcel_Worksheet.html" server="//nas/Web/crm/" local="129789909600000000" remote="129789909600000000" />
<file name="li_PHPExcel_Shared_ZipArchive.html" server="//nas/Web/crm/" local="129789909600000000" remote="129789909600000000" />
<file name="li_Math_Stats.html" server="//nas/Web/crm/" local="129789909600000000" remote="129789909600000000" />
<file name="li_PHPExcel_Writer_Excel2007.html" server="//nas/Web/crm/" local="129789909600000000" remote="129789909600000000" />
<file name="classtrees_PHPExcel_Worksheet.html" server="//nas/Web/crm/" local="129789909600000000" remote="129789909600000000" />
<file name="li_PHPExcel_Style.html" server="//nas/Web/crm/" local="129789909600000000" remote="129789909600000000" />
<file name="li_com-tecnick-tcpdf.html" server="//nas/Web/crm/" local="129789909600000000" remote="129789909600000000" />
<file name="index.html" server="//nas/Web/crm/" local="129789909600000000" remote="129789909600000000" />
<file name="li_PHPExcel_Shared_OLE.html" server="//nas/Web/crm/" local="129789909600000000" remote="129789909600000000" />
<file name="elementindex_PHPExcel_Shared_Escher.html" server="//nas/Web/crm/" local="129789909600000000" remote="129789909600000000" />
<file name="elementindex_PHPExcel_Writer_Excel2007.html" server="//nas/Web/crm/" local="129789909600000000" remote="129789909600000000" />
<file name="classtrees_PHPExcel_Reader.html" server="//nas/Web/crm/" local="129789909600000000" remote="129789909600000000" />
<file name="li_PHPExcel_CachedObjectStorage.html" server="//nas/Web/crm/" local="129789909600000000" remote="129789909600000000" />
<file name="elementindex_PHPExcel_Worksheet_Drawing.html" server="//nas/Web/crm/" local="129789909600000000" remote="129789909600000000" />
<file name="elementindex_PHPExcel_Reader_Excel2007.html" server="//nas/Web/crm/" local="129789909600000000" remote="129789909600000000" />
<file name="classtrees_PHPExcel_Writer_Excel5.html" server="//nas/Web/crm/" local="129789909600000000" remote="129789909600000000" />
<file name="elementindex_PHPExcel_Shared_ZipArchive.html" server="//nas/Web/crm/" local="129789909600000000" remote="129789909600000000" />
<file name="elementindex_PHPExcel_Style.html" server="//nas/Web/crm/" local="129789909600000000" remote="129789909600000000" />
<file name="classtrees_PHPExcel_Settings.html" server="//nas/Web/crm/" local="129789909600000000" remote="129789909600000000" />
<file name="li_PHPExcel_Shared_Best_Fit.html" server="//nas/Web/crm/" local="129789909600000000" remote="129789909600000000" />
<file name="elementindex.html" server="//nas/Web/crm/" local="129789909600000000" remote="129789909600000000" />
<file name="li_PHPExcel_Reader_Excel2007.html" server="//nas/Web/crm/" local="129789909600000000" remote="129789909600000000" />
<file name="elementindex_PHPExcel_Writer.html" server="//nas/Web/crm/" local="129789909600000000" remote="129789909600000000" />
<file name="elementindex_JAMA.html" server="//nas/Web/crm/" local="129789909600000000" remote="129789909600000000" />
<file name="elementindex_PHPExcel_RichText.html" server="//nas/Web/crm/" local="129789909600000000" remote="129789909600000000" />
<file name="li_PHPExcel_Worksheet_Drawing.html" server="//nas/Web/crm/" local="129789909600000000" remote="129789909600000000" />
<file name="classtrees_PHPExcel_Calculation.html" server="//nas/Web/crm/" local="129789909600000000" remote="129789909600000000" />
<file name="classtrees_PHPExcel_CachedObjectStorage.html" server="//nas/Web/crm/" local="129789909600000000" remote="129789909600000000" />
<file name="classtrees_PHPExcel_Reader_Excel2007.html" server="//nas/Web/crm/" local="129789909600000000" remote="129789909600000000" />
<file name="elementindex_PHPExcel_Settings.html" server="//nas/Web/crm/" local="129789909600000000" remote="129789909600000000" />
<file name="li_PHPExcel_Shared_Escher.html" server="//nas/Web/crm/" local="129789909600000000" remote="129789909600000000" />
<file name="elementindex_PHPExcel_Reader.html" server="//nas/Web/crm/" local="129789909600000000" remote="129789909600000000" />
<file name="classtrees_PHPExcel_Shared_Best_Fit.html" server="//nas/Web/crm/" local="129789909600000000" remote="129789909600000000" />
<file name="li_PHPExcel_Settings.html" server="//nas/Web/crm/" local="129789909600000000" remote="129789909600000000" />
<file name="todolist.html" server="//nas/Web/crm/" local="129789909600000000" remote="129789909600000000" />
<file name="li_PHPExcel_Writer_Excel5.html" server="//nas/Web/crm/" local="129789909600000000" remote="129789909600000000" />
<file name="li_PHPExcel_Cell.html" server="//nas/Web/crm/" local="129789909600000000" remote="129789909600000000" />
<file name="classtrees_PHPExcel_Shared_ZipArchive.html" server="//nas/Web/crm/" local="129789909600000000" remote="129789909600000000" />
<file name="classtrees_Math_Stats.html" server="//nas/Web/crm/" local="129789909600000000" remote="129789909600000000" />
<file name="classtrees_PHPExcel_Writer_Excel2007.html" server="//nas/Web/crm/" local="129789909600000000" remote="129789909600000000" />
<file name="errors.html" server="//nas/Web/crm/" local="129789909600000000" remote="129789909600000000" />
<file name="elementindex_PHPExcel_Calculation.html" server="//nas/Web/crm/" local="129789909600000000" remote="129789909600000000" />
<file name="li_PHPExcel_Worksheet.html" server="//nas/Web/crm/" local="129789909600000000" remote="129789909600000000" />
<file name="li_PHPExcel_Calculation.html" server="//nas/Web/crm/" local="129789909600000000" remote="129789909600000000" />
<file name="classtrees_PHPExcel_Style.html" server="//nas/Web/crm/" local="129789909600000000" remote="129789909600000000" />
</dwsync>